[{"id":"A001","patientId":"P001","roomId":"R001","admissionDate":"2025-11-01T10:00:00.000Z","dischargeDate":null,"status":"active","notes":"Observation for fever"},{"id":"A002","patientId":"P004","roomId":"R003","admissionDate":"2025-11-03T14:30:00.000Z","dischargeDate":null,"status":"active","notes":"Post-op recovery"},{"id":"A000","patientId":"P003","roomId":"R002","admissionDate":"2025-10-20T08:15:00.000Z","dischargeDate":"2025-10-23T09:00:00.000Z","status":"discharged","notes":"Stable at discharge"},{"id":"8359cbfd-5456-45d8-a152-7f7ad0aabb78","patientId":"P002","roomId":"R004","admissionDate":"2025-11-06T05:47:33.633174","dischargeDate":"2025-11-06T05:47:33.650408","status":"discharged","notes":"Observation"},{"id":"1d5a9e98-eafb-438d-8688-84c043c76af7","patientId":"P002","roomId":"R004","admissionDate":"2025-11-06T05:50:02.173172","dischargeDate":"2025-11-06T05:50:02.194908","status":"discharged","notes":"Observation"},{"id":"095d3e61-598e-4d8d-94c6-b647b23585b1","patientId":"P002","roomId":"R004","admissionDate":"2025-11-06T06:17:04.291255","dischargeDate":"2025-11-06T06:17:04.310254","status":"discharged","notes":"Observation"},{"id":"c8e1f1f2-11c0-4e7d-b8f6-755bf461e155","patientId":"P003","roomId":"R005","admissionDate":"2025-11-06T06:17:04.337254","dischargeDate":"2025-11-06T06:17:04.357299","status":"discharged","notes":"Initial stay"},{"id":"752ad0c3-8c8a-4482-8297-eb50445f23b7","patientId":"P002","roomId":"R004","admissionDate":"2025-11-06T06:19:42.994326","dischargeDate":"2025-11-06T06:19:43.018849","status":"discharged","notes":"Observation"},{"id":"376bfc29-1dd4-49d4-b4f3-adaa561f2734","patientId":"P003","roomId":"R005","admissionDate":"2025-11-06T06:19:43.043834","dischargeDate":"2025-11-06T06:19:43.062857","status":"discharged","notes":"Initial stay"},{"id":"50bd8f8a-ebd9-4d7a-a68a-90e687ef53fd","patientId":"P002","roomId":"R004","admissionDate":"2025-11-06T06:21:51.263009","dischargeDate":"2025-11-06T06:21:51.287","status":"discharged","notes":"Observation"},{"id":"d89e74cf-3b23-439e-9def-99090c0b15c6","patientId":"P003","roomId":"R005","admissionDate":"2025-11-06T06:21:51.313559","dischargeDate":"2025-11-06T06:21:51.334556","status":"discharged","notes":"Initial stay"}]